LICENSE.md
MANIFEST.in
README.md
jsonapi_datastore.py
setup.cfg
setup.py
jsonapi_datastore.egg-info/PKG-INFO
jsonapi_datastore.egg-info/SOURCES.txt
jsonapi_datastore.egg-info/dependency_links.txt
jsonapi_datastore.egg-info/not-zip-safe
jsonapi_datastore.egg-info/top_level.txt