Metadata-Version: 1.1
Name: jsonapi-datastore
Version: 0.1.2
Summary: A lightweight library handling structured JSONAPI responses.
Home-page: https://github.com/Tim-Erwin/python-jsonapi-datastore
Author: Tim-Christian Mundt
Author-email: dev@tim-erwin.de
License: UNKNOWN
Keywords: JSONAPI,JSON,API
Platform: UNKNOWN
Classifier: Development Status :: 5 - Production/Stable
Classifier: Intended Audience :: Developers
Classifier: License :: OSI Approved :: MIT License
Classifier: Programming Language :: Python :: 3
Classifier: Programming Language :: Python :: 3.3
Classifier: Programming Language :: Python :: 3.4
Classifier: Programming Language :: Python :: 3.5
Classifier: Programming Language :: Python :: Implementation :: CPython
Classifier: Programming Language :: Python :: Implementation :: PyPy
